Metadata-Version: 2.1
Name: bfscraper
Version: 0.1.1
Summary: Scrapes Betfair price data for Australian horse racing
Home-page: https://github.com/apapadimitriou/bfscraper
Author: Antony Papadimitriou
Author-email: antony.papadimitriou@icloud.com
License: UNKNOWN
Platform: UNKNOWN
Classifier: Programming Language :: Python :: 3
Classifier: License :: OSI Approved :: MIT License
Classifier: Operating System :: OS Independent
